{
  "docusaurus-plugin-content-docs": {
    "default": {
      "path": "/",
      "versions": [
        {
          "name": "current",
          "label": "Next",
          "isLast": true,
          "path": "/",
          "mainDocId": "index",
          "docs": [
            {
              "id": "community/ambassador-program",
              "path": "/community/ambassador-program",
              "sidebar": "docs"
            },
            {
              "id": "community/bi-weekly-calls",
              "path": "/community/bi-weekly-calls",
              "sidebar": "docs"
            },
            {
              "id": "community/code-of-conduct",
              "path": "/community/code-of-conduct",
              "sidebar": "docs"
            },
            {
              "id": "community/community-index",
              "path": "/community/",
              "sidebar": "docs"
            },
            {
              "id": "community/contributing",
              "path": "/community/contributing",
              "sidebar": "docs"
            },
            {
              "id": "community/roadmap",
              "path": "/community/roadmap",
              "sidebar": "docs"
            },
            {
              "id": "developer/architecture",
              "path": "/developer/architecture",
              "sidebar": "docs"
            },
            {
              "id": "developer/developer-index",
              "path": "/developer/",
              "sidebar": "docs"
            },
            {
              "id": "developer/local-dev",
              "path": "/developer/local-dev",
              "sidebar": "docs"
            },
            {
              "id": "developer/plugin-architecture",
              "path": "/developer/plugin-architecture",
              "sidebar": "docs"
            },
            {
              "id": "developer/release-process",
              "path": "/developer/release-process",
              "sidebar": "docs"
            },
            {
              "id": "developer/writing-tests",
              "path": "/developer/writing-tests",
              "sidebar": "docs"
            },
            {
              "id": "features/agents",
              "path": "/features/agents",
              "sidebar": "docs"
            },
            {
              "id": "features/ai-overview",
              "path": "/features/ai-overview",
              "sidebar": "docs"
            },
            {
              "id": "features/bar-charts",
              "path": "/features/bar-charts",
              "sidebar": "docs"
            },
            {
              "id": "features/charts-overview",
              "path": "/features/charts-overview",
              "sidebar": "docs"
            },
            {
              "id": "features/conversation-memory",
              "path": "/features/conversation-memory",
              "sidebar": "docs"
            },
            {
              "id": "features/csv-excel",
              "path": "/features/csv-excel",
              "sidebar": "docs"
            },
            {
              "id": "features/custom-prompts",
              "path": "/features/custom-prompts",
              "sidebar": "docs"
            },
            {
              "id": "features/data-sources-overview",
              "path": "/features/data-sources-overview",
              "sidebar": "docs"
            },
            {
              "id": "features/databases",
              "path": "/features/databases",
              "sidebar": "docs"
            },
            {
              "id": "features/deep-analysis",
              "path": "/features/deep-analysis",
              "sidebar": "docs"
            },
            {
              "id": "features/echarts-integration",
              "path": "/features/echarts-integration",
              "sidebar": "docs"
            },
            {
              "id": "features/features",
              "path": "/features/"
            },
            {
              "id": "features/heatmaps",
              "path": "/features/heatmaps",
              "sidebar": "docs"
            },
            {
              "id": "features/line-charts",
              "path": "/features/line-charts",
              "sidebar": "docs"
            },
            {
              "id": "features/natural-language-queries",
              "path": "/features/natural-language-queries",
              "sidebar": "docs"
            },
            {
              "id": "features/real-time-streams",
              "path": "/features/real-time-streams",
              "sidebar": "docs"
            },
            {
              "id": "features/warehouses",
              "path": "/features/warehouses",
              "sidebar": "docs"
            },
            {
              "id": "features/what-if-simulations",
              "path": "/features/what-if-simulations",
              "sidebar": "docs"
            },
            {
              "id": "getting-started/demo-walkthrough",
              "path": "/getting-started/demo-walkthrough",
              "sidebar": "docs"
            },
            {
              "id": "getting-started/faq",
              "path": "/getting-started/faq",
              "sidebar": "docs"
            },
            {
              "id": "getting-started/first-chart",
              "path": "/getting-started/first-chart",
              "sidebar": "docs"
            },
            {
              "id": "getting-started/getting-started",
              "path": "/getting-started/",
              "sidebar": "docs"
            },
            {
              "id": "getting-started/quick-start-docker",
              "path": "/getting-started/quick-start-docker",
              "sidebar": "docs"
            },
            {
              "id": "index",
              "path": "/",
              "sidebar": "docs"
            },
            {
              "id": "performance/performance-overview",
              "path": "/performance/",
              "sidebar": "docs"
            },
            {
              "id": "reference/api-reference",
              "path": "/reference/api-reference",
              "sidebar": "docs"
            },
            {
              "id": "reference/config-reference",
              "path": "/reference/config-reference",
              "sidebar": "docs"
            },
            {
              "id": "security/security-overview",
              "path": "/security/",
              "sidebar": "docs"
            },
            {
              "id": "self-host/backups",
              "path": "/self-host/backups",
              "sidebar": "docs"
            },
            {
              "id": "self-host/config-reference",
              "path": "/self-host/config-reference",
              "sidebar": "docs"
            },
            {
              "id": "self-host/docker-compose",
              "path": "/self-host/docker-compose",
              "sidebar": "docs"
            },
            {
              "id": "self-host/self-host-index",
              "path": "/self-host/",
              "sidebar": "docs"
            },
            {
              "id": "self-host/ssl-certificates",
              "path": "/self-host/ssl-certificates",
              "sidebar": "docs"
            },
            {
              "id": "troubleshooting/troubleshooting-overview",
              "path": "/troubleshooting/",
              "sidebar": "docs"
            }
          ],
          "draftIds": [],
          "sidebars": {
            "docs": {
              "link": {
                "path": "/",
                "label": "index"
              }
            }
          }
        }
      ],
      "breadcrumbs": true
    }
  }
}