{
  "id": "features/warehouses",
  "title": "Warehouses",
  "description": "Overview",
  "source": "@site/docs/features/warehouses.md",
  "sourceDirName": "features",
  "slug": "/features/warehouses",
  "permalink": "/docs/features/warehouses",
  "draft": false,
  "unlisted": false,
  "editUrl": "https://github.com/aiser-platform/aiser-world/edit/main/packages/docs/docs/features/warehouses.md",
  "tags": [],
  "version": "current",
  "lastUpdatedAt": 1539502055,
  "formattedLastUpdatedAt": "Oct 14, 2018",
  "frontMatter": {
    "id": "warehouses",
    "title": "Warehouses",
    "sidebar_label": "Warehouses"
  },
  "sidebar": "docs",
  "previous": {
    "title": "Databases",
    "permalink": "/docs/features/databases"
  },
  "next": {
    "title": "Real Time Streams",
    "permalink": "/docs/features/real-time-streams"
  }
}